{
  "name": "烟绯",
  "fullname": "烟绯",
  "title": "智明无邪",
  "description": "活跃在璃月港的知名律法咨询师，混有仙兽血脉的精明少女。",
  "rarity": "4",
  "element": "火",
  "weapontype": "法器",
  "substat": "火元素伤害加成",
  "gender": "女",
  "body": "GIRL",
  "association": "LIYUE",
  "region": "Liyue",
  "affiliation": "烟绯律法咨询事务所",
  "birthdaymmdd": "7/28",
  "birthday": "7月28日",
  "constellation": "法兽座",
  "cv": {
    "english": "莉琪·弗里曼",
    "chinese": "苏子芜",
    "japanese": "花守由美里",
    "korean": "赵京洢"
  },
  "costs": {
    "ascend1": [
      {
        "name": "摩拉",
        "count": 20000
      },
      {
        "name": "燃愿玛瑙碎屑",
        "count": 1
      },
      {
        "name": "夜泊石",
        "count": 3
      },
      {
        "name": "寻宝鸦印",
        "count": 3
      }
    ],
    "ascend2": [
      {
        "name": "摩拉",
        "count": 40000
      },
      {
        "name": "燃愿玛瑙断片",
        "count": 3
      },
      {
        "name": "未熟之玉",
        "count": 2
      },
      {
        "name": "夜泊石",
        "count": 10
      },
      {
        "name": "寻宝鸦印",
        "count": 15
      }
    ],
    "ascend3": [
      {
        "name": "摩拉",
        "count": 60000
      },
      {
        "name": "燃愿玛瑙断片",
        "count": 6
      },
      {
        "name": "未熟之玉",
        "count": 4
      },
      {
        "name": "夜泊石",
        "count": 20
      },
      {
        "name": "藏银鸦印",
        "count": 12
      }
    ],
    "ascend4": [
      {
        "name": "摩拉",
        "count": 80000
      },
      {
        "name": "燃愿玛瑙块",
        "count": 3
      },
      {
        "name": "未熟之玉",
        "count": 8
      },
      {
        "name": "夜泊石",
        "count": 30
      },
      {
        "name": "藏银鸦印",
        "count": 18
      }
    ],
    "ascend5": [
      {
        "name": "摩拉",
        "count": 100000
      },
      {
        "name": "燃愿玛瑙块",
        "count": 6
      },
      {
        "name": "未熟之玉",
        "count": 12
      },
      {
        "name": "夜泊石",
        "count": 45
      },
      {
        "name": "攫金鸦印",
        "count": 12
      }
    ],
    "ascend6": [
      {
        "name": "摩拉",
        "count": 120000
      },
      {
        "name": "燃愿玛瑙",
        "count": 6
      },
      {
        "name": "未熟之玉",
        "count": 20
      },
      {
        "name": "夜泊石",
        "count": 60
      },
      {
        "name": "攫金鸦印",
        "count": 24
      }
    ]
  },
  "images": {
    "cover1": "https://uploadstatic-sea.hoyoverse.com/contentweb/20210421/2021042114214196211.png",
    "cover2": "https://uploadstatic-sea.hoyoverse.com/contentweb/20210421/2021042114231180906.png",
    "icon": "https://upload-os-bbs.mihoyo.com/game_record/genshin/character_icon/UI_AvatarIcon_Feiyan.png",
    "sideicon": "https://upload-os-bbs.mihoyo.com/game_record/genshin/character_side_icon/UI_AvatarIcon_Side_Feiyan.png",
    "hoyolab-avatar": "https://img-os-static.hoyolab.com/communityWeb/upload/75c1d48b2fa08bd4c583501a3bb476d3.png",
    "nameicon": "UI_AvatarIcon_Feiyan",
    "nameiconcard": "UI_AvatarIcon_Feiyan_Card",
    "namegachasplash": "UI_Gacha_AvatarImg_Feiyan",
    "namegachaslice": "UI_Gacha_AvatarIcon_Feiyan",
    "namesideicon": "UI_AvatarIcon_Side_Feiyan"
  },
  "url": {
    "fandom": "https://genshin-impact.fandom.com/wiki/Yanfei"
  },
  "stats": {
    "s1": {
      "level": 1,
      "ascension": 0,
      "hp": 784.1402587890625,
      "attack": 20.12303924560547,
      "defense": 49.2135009765625,
      "specialized": 0
    },
    "s20": {
      "level": 20,
      "ascension": 0,
      "hp": 2014.4563293159881,
      "attack": 51.6960879371054,
      "defense": 126.42948429039097,
      "specialized": 0
    },
    "s20p": {
      "level": 20,
      "ascension": 1,
      "hp": 2600.249237030832,
      "attack": 66.72938166116546,
      "defense": 163.1944836800394,
      "specialized": 0
    },
    "s40": {
      "level": 40,
      "ascension": 1,
      "hp": 3894.864635285514,
      "attack": 99.95251511853348,
      "defense": 244.44596318533877,
      "specialized": 0
    },
    "s40p": {
      "level": 40,
      "ascension": 2,
      "hp": 4311.085948762076,
      "attack": 110.63406705182206,
      "defense": 270.5684645586298,
      "specialized": 0.05999999865889549
    },
    "s50": {
      "level": 50,
      "ascension": 2,
      "hp": 4958.785970032273,
      "attack": 127.25570176743713,
      "defense": 311.21882687840844,
      "specialized": 0.05999999865889549
    },
    "s50p": {
      "level": 50,
      "ascension": 3,
      "hp": 5513.747700989305,
      "attack": 141.49776910447326,
      "defense": 346.04882489476586,
      "specialized": 0.11999999731779099
    },
    "s60": {
      "level": 60,
      "ascension": 3,
      "hp": 6161.4477222595015,
      "attack": 158.11940382008834,
      "defense": 386.6991872145445,
      "specialized": 0.11999999731779099
    },
    "s60p": {
      "level": 60,
      "ascension": 4,
      "hp": 6577.669035736064,
      "attack": 168.80095670705123,
      "defense": 412.82168477313826,
      "specialized": 0.11999999731779099
    },
    "s70": {
      "level": 70,
      "ascension": 4,
      "hp": 7224.5845996741555,
      "attack": 185.4024602465106,
      "defense": 453.42281369207194,
      "specialized": 0.11999999731779099
    },
    "s70p": {
      "level": 70,
      "ascension": 5,
      "hp": 7640.8057910804055,
      "attack": 196.08400931877622,
      "defense": 479.5453112506657,
      "specialized": 0.18000000715255737
    },
    "s80": {
      "level": 80,
      "ascension": 5,
      "hp": 8288.50543844339,
      "attack": 212.70563443897845,
      "defense": 520.1956501036184,
      "specialized": 0.18000000715255737
    },
    "s80p": {
      "level": 80,
      "ascension": 6,
      "hp": 8704.726873990265,
      "attack": 223.38718351124407,
      "defense": 546.3181629210012,
      "specialized": 0.23999999463558197
    },
    "s90": {
      "level": 90,
      "ascension": 6,
      "hp": 9352.426895260462,
      "attack": 240.00881822685915,
      "defense": 586.9685252407799,
      "specialized": 0.23999999463558197
    }
  },
  "version": "1.5",
  "constellations": {
    "c1": {
      "name": "占理不饶人",
      "effect": "烟绯进行重击时，每持有一枚丹火印，都会提高烟绯在咏唱期间的抗打断能力，并额外降低本次重击10%的体力消耗。"
    },
    "c2": {
      "name": "最终解释权",
      "effect": "烟绯的重击对于生命值低于50%的敌人，暴击率提高20%。"
    },
    "c3": {
      "name": "真火炼宝印",
      "effect": "**丹书立约**的技能等级提高3级。\n至多提升至15级。"
    },
    "c4": {
      "name": "丹书金铁券",
      "effect": "施放**凭此结契**时：\n生成一个伤害吸收量等于生命值上限45%的护盾，持续15秒。\n该护盾对火元素伤害有250%的吸收效果。"
    },
    "c5": {
      "name": "遵法切结书",
      "effect": "**凭此结契**的技能等级提高3级。\n至多提升至15级。"
    },
    "c6": {
      "name": "是额外条款",
      "effect": "烟绯持有的丹火印最大数量增加一枚。"
    },
    "images": {
      "c1": "https://upload-os-bbs.mihoyo.com/game_record/genshin/constellation_icon/UI_Talent_S_Feiyan_01.png",
      "c2": "https://upload-os-bbs.mihoyo.com/game_record/genshin/constellation_icon/UI_Talent_S_Feiyan_02.png",
      "c3": "https://upload-os-bbs.mihoyo.com/game_record/genshin/constellation_icon/UI_Talent_U_Feiyan_01.png",
      "c4": "https://upload-os-bbs.mihoyo.com/game_record/genshin/constellation_icon/UI_Talent_S_Feiyan_03.png",
      "c5": "https://upload-os-bbs.mihoyo.com/game_record/genshin/constellation_icon/UI_Talent_U_Feiyan_02.png",
      "c6": "https://upload-os-bbs.mihoyo.com/game_record/genshin/constellation_icon/UI_Talent_S_Feiyan_04.png",
      "constellation": "Eff_UI_Talent_Feiyan"
    },
    "version": "1.5"
  },
  "talent": {
    "name": "烟绯",
    "combat1": {
      "name": "普通攻击·火漆制印",
      "info": "**普通攻击**\n连续发射火球，造成最多三段的火元素伤害。\n普通攻击命中敌人时，会赋予烟绯一枚丹火印。初始最多持有三枚丹火印，每次触发都会刷新已有的丹火印持续时间。\n每枚丹火印都会降低烟绯的体力消耗，并会在烟绯退场时消失。\n\n**重击**\n消耗体力，短暂咏唱后，消耗所有的丹火印，在前方造成火元素范围伤害。\n根据被消耗的丹火印数量，强化这次重击的范围与伤害。\n\n**下落攻击**\n凝聚火元素的力量，从空中下坠冲击地面，攻击下落路径上的敌人，并在落地时造成火元素范围伤害。",
      "attributes": [
        {
          "name": "一段伤害",
          "parameters": [
            "58.34%",
            "62.72%",
            "67.09%",
            "72.93%",
            "77.30%",
            "81.68%",
            "87.51%",
            "93.35%",
            "99.18%",
            "105.01%",
            "110.85%",
            "116.68%",
            "123.98%",
            "131.27%",
            "138.56%"
          ]
        },
        {
          "name": "二段伤害",
          "parameters": [
            "52.13%",
            "56.04%",
            "59.94%",
            "65.16%",
            "69.07%",
            "72.98%",
            "78.19%",
            "83.40%",
            "88.61%",
            "93.83%",
            "99.04%",
            "104.25%",
            "110.77%",
            "117.28%",
            "123.80%"
          ]
        },
        {
          "name": "三段伤害",
          "parameters": [
            "76.01%",
            "81.71%",
            "87.41%",
            "95.02%",
            "100.72%",
            "106.42%",
            "114.02%",
            "121.62%",
            "129.22%",
            "136.82%",
            "144.42%",
            "152.03%",
            "161.53%",
            "171.03%",
            "180.53%"
          ]
        },
        {
          "name": "重击伤害",
          "parameters": [
            "98.23%/115.56%/132.90%/150.23%/167.57%",
            "104.11%/122.48%/140.86%/159.23%/177.60%",
            "109.99%/129.40%/148.81%/168.23%/187.64%",
            "117.64%/138.40%/159.16%/179.92%/200.68%",
            "123.52%/145.32%/167.12%/188.92%/210.71%",
            "129.40%/152.24%/175.08%/197.91%/220.75%",
            "137.05%/161.24%/185.42%/209.61%/233.79%",
            "144.70%/170.23%/195.77%/221.30%/246.84%",
            "152.34%/179.23%/206.11%/233.00%/259.88%",
            "159.99%/188.22%/216.46%/244.69%/272.92%",
            "167.64%/197.22%/226.80%/256.39%/285.97%",
            "175.28%/206.22%/237.15%/268.08%/299.01%",
            "182.93%/215.21%/247.49%/279.78%/312.06%",
            "190.58%/224.21%/257.84%/291.47%/325.10%",
            "198.22%/233.20%/268.18%/303.17%/338.15%"
          ]
        },
        {
          "name": "重击体力消耗",
          "parameters": [
            "50点",
            "50点",
            "50点",
            "50点",
            "50点",
            "50点",
            "50点",
            "50点",
            "50点",
            "50点",
            "50点",
            "50点",
            "50点",
            "50点",
            "50点"
          ]
        },
        {
          "name": "丹火印降低体力消耗",
          "parameters": [
            "每枚15.00%",
            "每枚15.00%",
            "每枚15.00%",
            "每枚15.00%",
            "每枚15.00%",
            "每枚15.00%",
            "每枚15.00%",
            "每枚15.00%",
            "每枚15.00%",
            "每枚15.00%",
            "每枚15.00%",
            "每枚15.00%",
            "每枚15.00%",
            "每枚15.00%",
            "每枚15.00%"
          ]
        },
        {
          "name": "丹火印持续时间",
          "parameters": [
            "10秒",
            "10秒",
            "10秒",
            "10秒",
            "10秒",
            "10秒",
            "10秒",
            "10秒",
            "10秒",
            "10秒",
            "10秒",
            "10秒",
            "10秒",
            "10秒",
            "10秒"
          ]
        },
        {
          "name": "下坠期间伤害",
          "parameters": [
            "56.83%",
            "61.45%",
            "66.08%",
            "72.69%",
            "77.31%",
            "82.60%",
            "89.87%",
            "97.14%",
            "104.41%",
            "112.34%",
            "120.27%",
            "128.20%",
            "136.12%",
            "144.05%",
            "151.98%"
          ]
        },
        {
          "name": "低空/高空坠地冲击伤害",
          "parameters": [
            "113.63%/141.93%",
            "122.88%/153.49%",
            "132.13%/165.04%",
            "145.35%/181.54%",
            "154.59%/193.10%",
            "165.16%/206.30%",
            "179.70%/224.45%",
            "194.23%/242.61%",
            "208.77%/260.76%",
            "224.62%/280.57%",
            "240.48%/300.37%",
            "256.34%/320.18%",
            "272.19%/339.98%",
            "288.05%/359.79%",
            "303.90%/379.59%"
          ]
        }
      ]
    },
    "combat2": {
      "name": "丹书立约",
      "info": "唤出烈焰，造成火元素范围伤害。\n命中敌人后，会为烟绯赋予最大数量的丹火印。",
      "description": "以火烧制的印除了法律效应之外，还带着烟绯自己的附加条款。毕竟自然法则只靠总务司是改不掉的。",
      "attributes": [
        {
          "name": "技能伤害",
          "parameters": [
            "169.60%",
            "182.32%",
            "195.04%",
            "212.00%",
            "224.72%",
            "237.44%",
            "254.40%",
            "271.36%",
            "288.32%",
            "305.28%",
            "322.24%",
            "339.20%",
            "360.40%",
            "381.60%",
            "402.80%"
          ]
        },
        {
          "name": "冷却时间",
          "parameters": [
            "9秒",
            "9秒",
            "9秒",
            "9秒",
            "9秒",
            "9秒",
            "9秒",
            "9秒",
            "9秒",
            "9秒",
            "9秒",
            "9秒",
            "9秒",
            "9秒",
            "9秒"
          ]
        }
      ]
    },
    "combat3": {
      "name": "凭此结契",
      "info": "引发喷薄爆发的烈火，冲击周围的敌人，造成火元素范围伤害，并为烟绯自己赋予最大数量的丹火印与灼灼效果。\n\n**灼灼**\n具有如下效果：\n·每间隔一段时间，为烟绯赋予一枚丹火印；\n·提高重击造成的伤害。\n灼灼效果会在烟绯退场与倒下时移除。",
      "description": "「条款齐备，依此立下生死之契。当然，是你死我生啦！」",
      "attributes": [
        {
          "name": "技能伤害",
          "parameters": [
            "182.40%",
            "196.08%",
            "209.76%",
            "228.00%",
            "241.68%",
            "255.36%",
            "273.60%",
            "291.84%",
            "310.08%",
            "328.32%",
            "346.56%",
            "364.80%",
            "387.60%",
            "410.40%",
            "433.20%"
          ]
        },
        {
          "name": "丹火印赋予间隔",
          "parameters": [
            "1秒",
            "1秒",
            "1秒",
            "1秒",
            "1秒",
            "1秒",
            "1秒",
            "1秒",
            "1秒",
            "1秒",
            "1秒",
            "1秒",
            "1秒",
            "1秒",
            "1秒"
          ]
        },
        {
          "name": "重击伤害提升",
          "parameters": [
            "33.40%",
            "35.40%",
            "37.40%",
            "40.00%",
            "42.00%",
            "44.00%",
            "46.60%",
            "49.20%",
            "51.80%",
            "54.40%",
            "57.00%",
            "59.60%",
            "62.20%",
            "64.80%",
            "67.40%"
          ]
        },
        {
          "name": "持续时间",
          "parameters": [
            "15秒",
            "15秒",
            "15秒",
            "15秒",
            "15秒",
            "15秒",
            "15秒",
            "15秒",
            "15秒",
            "15秒",
            "15秒",
            "15秒",
            "15秒",
            "15秒",
            "15秒"
          ]
        },
        {
          "name": "冷却时间",
          "parameters": [
            "20秒",
            "20秒",
            "20秒",
            "20秒",
            "20秒",
            "20秒",
            "20秒",
            "20秒",
            "20秒",
            "20秒",
            "20秒",
            "20秒",
            "20秒",
            "20秒",
            "20秒"
          ]
        },
        {
          "name": "元素能量",
          "parameters": [
            "80",
            "80",
            "80",
            "80",
            "80",
            "80",
            "80",
            "80",
            "80",
            "80",
            "80",
            "80",
            "80",
            "80",
            "80"
          ]
        }
      ]
    },
    "passive1": {
      "name": "关联条款",
      "info": "烟绯通过重击消耗丹火印时，每枚丹火印会提升烟绯5%的火元素伤害加成，持续6秒。在该效果的持续时间内再次施放重击时，会先移除原有的效果。"
    },
    "passive2": {
      "name": "法兽灼眼",
      "info": "烟绯主动施放的重击对敌人造成暴击时，会额外造成一次80%攻击力的火元素范围伤害。该伤害视为重击伤害。"
    },
    "passive3": {
      "name": "博闻强记",
      "info": "在小地图上显示周围的**璃月区域特产**的位置。"
    },
    "costs": {
      "lvl2": [
        {
          "name": "摩拉",
          "count": 12500
        },
        {
          "name": "「黄金」的教导",
          "count": 3
        },
        {
          "name": "寻宝鸦印",
          "count": 6
        }
      ],
      "lvl3": [
        {
          "name": "摩拉",
          "count": 17500
        },
        {
          "name": "「黄金」的指引",
          "count": 2
        },
        {
          "name": "藏银鸦印",
          "count": 3
        }
      ],
      "lvl4": [
        {
          "name": "摩拉",
          "count": 25000
        },
        {
          "name": "「黄金」的指引",
          "count": 4
        },
        {
          "name": "藏银鸦印",
          "count": 4
        }
      ],
      "lvl5": [
        {
          "name": "摩拉",
          "count": 30000
        },
        {
          "name": "「黄金」的指引",
          "count": 6
        },
        {
          "name": "藏银鸦印",
          "count": 6
        }
      ],
      "lvl6": [
        {
          "name": "摩拉",
          "count": 37500
        },
        {
          "name": "「黄金」的指引",
          "count": 9
        },
        {
          "name": "藏银鸦印",
          "count": 9
        }
      ],
      "lvl7": [
        {
          "name": "摩拉",
          "count": 120000
        },
        {
          "name": "「黄金」的哲学",
          "count": 4
        },
        {
          "name": "攫金鸦印",
          "count": 4
        },
        {
          "name": "血玉之枝",
          "count": 1
        }
      ],
      "lvl8": [
        {
          "name": "摩拉",
          "count": 260000
        },
        {
          "name": "「黄金」的哲学",
          "count": 6
        },
        {
          "name": "攫金鸦印",
          "count": 6
        },
        {
          "name": "血玉之枝",
          "count": 1
        }
      ],
      "lvl9": [
        {
          "name": "摩拉",
          "count": 450000
        },
        {
          "name": "「黄金」的哲学",
          "count": 12
        },
        {
          "name": "攫金鸦印",
          "count": 9
        },
        {
          "name": "血玉之枝",
          "count": 2
        }
      ],
      "lvl10": [
        {
          "name": "摩拉",
          "count": 700000
        },
        {
          "name": "「黄金」的哲学",
          "count": 16
        },
        {
          "name": "攫金鸦印",
          "count": 12
        },
        {
          "name": "血玉之枝",
          "count": 2
        },
        {
          "name": "智识之冕",
          "count": 1
        }
      ]
    },
    "images": {
      "combat1": "Skill_A_Catalyst_MD",
      "combat2": "Skill_S_Feiyan_01",
      "combat3": "Skill_E_Feiyan_01_HD",
      "passive1": "UI_Talent_S_Feiyan_05",
      "passive2": "UI_Talent_S_Feiyan_06",
      "passive3": "UI_Talent_Collect_Local_Liyue"
    },
    "version": "1.5"
  }
}