{
  "name": "幼岩龙蜥",
  "specialname": "梦想成为巨龙的幼兽",
  "enemytype": "ELITE",
  "category": "异种魔兽",
  "description": "有着坚硬岩质甲壳的小型龙蜥。\n行动非常灵活，是不容小觑的对手。须弥教令院的研究认为，即使是这种幼兽，也有成为「龙」的潜质。假以时日，如果不受天灾与敌害，或许也有一天能成为撼动高山的巨大魔物吧。",
  "investigation": {
    "name": "幼岩龙蜥",
    "category": "精英",
    "description": "有着坚硬岩质甲壳的小型龙蜥。\\n行动非常灵活，是不容小觑的对手。须弥教令院的研究认为，即使是这种幼兽，也有成为「龙」的潜质。假以时日，如果不受天灾与敌害，或许也有一天能成为撼动高山的巨大魔物吧。"
  },
  "rewardpreview": [
    {
      "name": "摩拉"
    },
    {
      "name": "脆弱的骨片",
      "count": 5.2526
    },
    {
      "name": "结实的骨片",
      "count": 1.4006
    },
    {
      "name": "石化的骨片",
      "count": 0.3502
    },
    {
      "name": "战狂",
      "rarity": "3"
    },
    {
      "name": "教官",
      "rarity": "3"
    },
    {
      "name": "流放者",
      "rarity": "3"
    },
    {
      "name": "游医",
      "rarity": "3"
    },
    {
      "name": "战狂",
      "rarity": "4"
    },
    {
      "name": "教官",
      "rarity": "4"
    },
    {
      "name": "流放者",
      "rarity": "4"
    }
  ],
  "images": {
    "nameicon": "UI_MonsterIcon_Wyrm_Rock"
  },
  "stats": [
    {
      "level": 1,
      "hp": 218.7509794542566,
      "attack": 60.906552212361476,
      "defense": 505
    },
    {
      "level": 10,
      "hp": 859.8121607497742,
      "attack": 162.72665734099883,
      "defense": 550
    },
    {
      "level": 20,
      "hp": 2655.600003847154,
      "attack": 401.39990634691276,
      "defense": 600
    },
    {
      "level": 30,
      "hp": 4418.400979883387,
      "attack": 655.6238161127621,
      "defense": 650
    },
    {
      "level": 40,
      "hp": 8084.548390447162,
      "attack": 980.1932871321915,
      "defense": 700
    },
    {
      "level": 50,
      "hp": 14989.452767774463,
      "attack": 1511.5853374239596,
      "defense": 750
    },
    {
      "level": 60,
      "hp": 25143.764439336956,
      "attack": 2128.6184320330067,
      "defense": 800
    },
    {
      "level": 70,
      "hp": 39155.91791216936,
      "attack": 2938.457141733408,
      "defense": 850
    },
    {
      "level": 80,
      "hp": 55697.182621506974,
      "attack": 3780.6359339640476,
      "defense": 900
    },
    {
      "level": 90,
      "hp": 73062.26003226824,
      "attack": 4567.52926300207,
      "defense": 950
    },
    {
      "level": 100,
      "hp": 110295.36462029815,
      "attack": 5909.301052030816,
      "defense": 1000
    },
    {
      "level": 110,
      "hp": 160506.94116508216,
      "attack": 6026.632944034442,
      "defense": 1050
    },
    {
      "level": 120,
      "hp": 215958.9501701519,
      "attack": 6144.786326247908,
      "defense": 1100
    }
  ],
  "version": ""
}