{
  "name": "Благословение: Элегия инея",
  "region": "Мондштадт",
  "domainEntrance": "Пик Виндагнира",
  "domainType": "Артефакты",
  "description": "Давным-давно это место использовалось для проведения ритуалов и касалось небес, но упавший Шип небесной стужи похоронил его в склоне горы. Гуляющий по его залам морозный воздух создал уникальную среду. Чтобы пройти испытание, вам придётся пересилить лютый мороз...",
  "daysOfWeek": null,
  "images": {
    "namepic": "UI_DungeonPic_Cubic_Cold_1"
  },
  "version": "",
  "domainLevels": [
    {
      "name": "Благословение: Элегия инея I",
      "recommendedLevel": 59,
      "recommendedElements": [
        "Пиро",
        "Электро",
        "Гео",
        "Анемо"
      ],
      "unlockRank": 30,
      "rewardPreview": [
        {
          "name": "Опыт приключений",
          "count": 100
        },
        {
          "name": "Мора",
          "count": 1850
        },
        {
          "name": "Опыт дружбы",
          "count": 15
        },
        {
          "name": "Воля защитника",
          "rarity": "3"
        },
        {
          "name": "Азартный игрок",
          "rarity": "3"
        },
        {
          "name": "Заблудший в метели",
          "rarity": "4"
        },
        {
          "name": "Сердце глубин",
          "rarity": "4"
        },
        {
          "name": "Воля защитника",
          "rarity": "4"
        },
        {
          "name": "Азартный игрок",
          "rarity": "4"
        }
      ],
      "disorder": [
        "Персонажи на платформе испытания постоянно накапливают лютый мороз и будут терять HP, если лютый мороз достигнет предела.",
        "Платформа испытания периодически переключается между тёплым и холодным режимом.",
        "Тёплые поверхности снижают накопленный лютый мороз, а холодные поверхности ускоряют его накопление."
      ],
      "monsterlist": [
        "Крио слайм",
        "Большой Крио слайм",
        "Митачурл с ледяным щитом"
      ]
    },
    {
      "name": "Благословение: Элегия инея II",
      "recommendedLevel": 69,
      "recommendedElements": [
        "Пиро",
        "Электро",
        "Гео",
        "Анемо"
      ],
      "unlockRank": 35,
      "rewardPreview": [
        {
          "name": "Опыт приключений",
          "count": 100
        },
        {
          "name": "Мора",
          "count": 2025
        },
        {
          "name": "Опыт дружбы",
          "count": 20
        },
        {
          "name": "Воля защитника",
          "rarity": "3"
        },
        {
          "name": "Азартный игрок",
          "rarity": "3"
        },
        {
          "name": "Заблудший в метели",
          "rarity": "4"
        },
        {
          "name": "Сердце глубин",
          "rarity": "4"
        },
        {
          "name": "Воля защитника",
          "rarity": "4"
        },
        {
          "name": "Азартный игрок",
          "rarity": "4"
        }
      ],
      "disorder": [
        "Персонажи на платформе испытания постоянно накапливают лютый мороз и будут терять HP, если лютый мороз достигнет предела.",
        "Платформа испытания периодически переключается между тёплым и холодным режимом.",
        "Тёплые поверхности снижают накопленный лютый мороз, а холодные поверхности ускоряют его накопление."
      ],
      "monsterlist": [
        "Крио слайм",
        "Большой Крио слайм",
        "Крио хиличурл-гренадёр",
        "Митачурл с ледяным щитом"
      ]
    },
    {
      "name": "Благословение: Элегия инея III",
      "recommendedLevel": 80,
      "recommendedElements": [
        "Пиро",
        "Электро",
        "Гео",
        "Анемо"
      ],
      "unlockRank": 40,
      "rewardPreview": [
        {
          "name": "Опыт приключений",
          "count": 100
        },
        {
          "name": "Мора",
          "count": 2200
        },
        {
          "name": "Опыт дружбы",
          "count": 20
        },
        {
          "name": "Воля защитника",
          "rarity": "3"
        },
        {
          "name": "Азартный игрок",
          "rarity": "3"
        },
        {
          "name": "Заблудший в метели",
          "rarity": "4"
        },
        {
          "name": "Сердце глубин",
          "rarity": "4"
        },
        {
          "name": "Воля защитника",
          "rarity": "4"
        },
        {
          "name": "Азартный игрок",
          "rarity": "4"
        },
        {
          "name": "Заблудший в метели",
          "rarity": "5"
        },
        {
          "name": "Сердце глубин",
          "rarity": "5"
        }
      ],
      "disorder": [
        "Персонажи на платформе испытания постоянно накапливают лютый мороз и будут терять HP, если лютый мороз достигнет предела.",
        "Платформа испытания периодически переключается между тёплым и холодным режимом.",
        "Тёплые поверхности снижают накопленный лютый мороз, а холодные поверхности ускоряют его накопление."
      ],
      "monsterlist": [
        "Большой Крио слайм",
        "Крио хиличурл-гренадёр",
        "Митачурл с ледяным щитом",
        "Крио маг Бездны"
      ]
    },
    {
      "name": "Благословение: Элегия инея IV",
      "recommendedLevel": 90,
      "recommendedElements": [
        "Пиро",
        "Электро",
        "Гео",
        "Анемо"
      ],
      "unlockRank": 45,
      "rewardPreview": [
        {
          "name": "Опыт приключений",
          "count": 100
        },
        {
          "name": "Мора",
          "count": 2525
        },
        {
          "name": "Опыт дружбы",
          "count": 20
        },
        {
          "name": "Воля защитника",
          "rarity": "3"
        },
        {
          "name": "Азартный игрок",
          "rarity": "3"
        },
        {
          "name": "Заблудший в метели",
          "rarity": "4"
        },
        {
          "name": "Сердце глубин",
          "rarity": "4"
        },
        {
          "name": "Воля защитника",
          "rarity": "4"
        },
        {
          "name": "Азартный игрок",
          "rarity": "4"
        },
        {
          "name": "Заблудший в метели",
          "rarity": "5"
        },
        {
          "name": "Сердце глубин",
          "rarity": "5"
        }
      ],
      "disorder": [
        "Персонажи на платформе испытания постоянно накапливают лютый мороз и будут терять HP, если лютый мороз достигнет предела.",
        "Платформа испытания периодически переключается между тёплым и холодным режимом.",
        "Тёплые поверхности снижают накопленный лютый мороз, а холодные поверхности ускоряют его накопление."
      ],
      "monsterlist": [
        "Лавачурл с инеевым панцирем",
        "Крио маг Бездны"
      ]
    }
  ]
}