{
  "name": "Tea-Colored Shirakodai",
  "description": "Varian ikan kupu-kupu yang lembut dan elegan. Mereka memiliki sirip punggung yang indah dan ramping, serta julukan \"Ratu Perairan\".\nPola-pola berwarna teh menghiasi sekujur tubuhnya. Ikan yang penuh rasa penasaran ini tampak sangat tertarik pada segala sesuatu di sekitarnya. Sayangnya, cara mereka menyampaikan minatnya tersebut adalah dengan cara menggigit untuk melihat apakah benda itu bisa dimakan atau tidak. Tindakan ini sama sekali tidak mengandung niat jahat, namun gara-gara tindakan tersebut, mereka seringkali harus berhadapan dengan bencana yang sangat fatal.",
  "sortorder": 2029,
  "rarity": "3",
  "category": "EXCHANGE",
  "materialtype": "Ikan",
  "source": [
    "Didapatkan dari memancing ikan"
  ],
  "images": {
    "redirect": "https://genshin-impact.fandom.com/wiki/Special:Redirect/file/Item_Tea-Colored_Shirakodai.png",
    "fandom": "https://static.wikia.nocookie.net/gensin-impact/images/0/0f/Item_Tea-Colored_Shirakodai.png",
    "nameicon": "UI_ItemIcon_131015"
  },
  "url": {
    "fandom": "https://genshin-impact.fandom.com/wiki/Tea-Colored_Shirakodai"
  },
  "version": ""
}