{
  "name": "치치",
  "fullname": "치치",
  "title": "차가운 환혼의 밤",
  "description": "약방 「불복려」의 약초꾼이자 제자. 안색이 종이처럼 창백하다. 말수가 적고 무표정하다",
  "rarity": "5",
  "element": "얼음",
  "weapontype": "한손검",
  "substat": "치유 보너스",
  "gender": "여성",
  "body": "LOLI",
  "association": "LIYUE",
  "region": "Liyue",
  "affiliation": "불복려",
  "birthdaymmdd": "3/3",
  "birthday": "3월 3일",
  "constellation": "삼청령자리",
  "cv": {
    "english": "Christie Cate",
    "chinese": "宴宁",
    "japanese": "Tamura Yukari",
    "korean": "이슬"
  },
  "costs": {
    "ascend1": [
      {
        "name": "모라",
        "count": 20000
      },
      {
        "name": "서늘한 빙옥 가루",
        "count": 1
      },
      {
        "name": "유리주머니",
        "count": 3
      },
      {
        "name": "이능 두루마리",
        "count": 3
      }
    ],
    "ascend2": [
      {
        "name": "모라",
        "count": 40000
      },
      {
        "name": "서늘한 빙옥 조각",
        "count": 3
      },
      {
        "name": "서리의 핵",
        "count": 2
      },
      {
        "name": "유리주머니",
        "count": 10
      },
      {
        "name": "이능 두루마리",
        "count": 15
      }
    ],
    "ascend3": [
      {
        "name": "모라",
        "count": 60000
      },
      {
        "name": "서늘한 빙옥 조각",
        "count": 6
      },
      {
        "name": "서리의 핵",
        "count": 4
      },
      {
        "name": "유리주머니",
        "count": 20
      },
      {
        "name": "봉마의 두루마리",
        "count": 12
      }
    ],
    "ascend4": [
      {
        "name": "모라",
        "count": 80000
      },
      {
        "name": "서늘한 빙옥 덩이",
        "count": 3
      },
      {
        "name": "서리의 핵",
        "count": 8
      },
      {
        "name": "유리주머니",
        "count": 30
      },
      {
        "name": "봉마의 두루마리",
        "count": 18
      }
    ],
    "ascend5": [
      {
        "name": "모라",
        "count": 100000
      },
      {
        "name": "서늘한 빙옥 덩이",
        "count": 6
      },
      {
        "name": "서리의 핵",
        "count": 12
      },
      {
        "name": "유리주머니",
        "count": 45
      },
      {
        "name": "금주의 두루마리",
        "count": 12
      }
    ],
    "ascend6": [
      {
        "name": "모라",
        "count": 120000
      },
      {
        "name": "서늘한 빙옥",
        "count": 6
      },
      {
        "name": "서리의 핵",
        "count": 20
      },
      {
        "name": "유리주머니",
        "count": 60
      },
      {
        "name": "금주의 두루마리",
        "count": 24
      }
    ]
  },
  "images": {
    "card": "https://static.wikia.nocookie.net/gensin-impact/images/b/b9/Character_Qiqi_Card.jpg",
    "portrait": "https://static.wikia.nocookie.net/gensin-impact/images/2/2a/Character_Qiqi_Portrait.png",
    "icon": "https://upload-os-bbs.mihoyo.com/game_record/genshin/character_icon/UI_AvatarIcon_Qiqi.png",
    "sideicon": "https://upload-os-bbs.mihoyo.com/game_record/genshin/character_side_icon/UI_AvatarIcon_Side_Qiqi.png",
    "cover1": "https://uploadstatic-sea.hoyoverse.com/contentweb/20200828/2020082817145380161.png",
    "cover2": "https://uploadstatic-sea.hoyoverse.com/contentweb/20200828/2020082817153781489.png",
    "hoyolab-avatar": "https://img-os-static.hoyolab.com/communityWeb/upload/d696551575bc6c117462563fc92eae6c.png",
    "nameicon": "UI_AvatarIcon_Qiqi",
    "nameiconcard": "UI_AvatarIcon_Qiqi_Card",
    "namegachasplash": "UI_Gacha_AvatarImg_Qiqi",
    "namegachaslice": "UI_Gacha_AvatarIcon_Qiqi",
    "namesideicon": "UI_AvatarIcon_Side_Qiqi"
  },
  "url": {
    "fandom": "https://genshin-impact.fandom.com/wiki/Qiqi"
  },
  "stats": {
    "s1": {
      "level": 1,
      "ascension": 0,
      "hp": 962.8532104492188,
      "attack": 22.3439998626709,
      "defense": 71.7959976196289,
      "specialized": 0
    },
    "s20": {
      "level": 20,
      "ascension": 0,
      "hp": 2497.6413252396014,
      "attack": 57.96033790251158,
      "defense": 186.23882508313727,
      "specialized": 0
    },
    "s20p": {
      "level": 20,
      "ascension": 1,
      "hp": 3323.2008955521014,
      "attack": 77.11689880033873,
      "defense": 247.7988264564283,
      "specialized": 0
    },
    "s40": {
      "level": 40,
      "ascension": 1,
      "hp": 4972.5685019830125,
      "attack": 115.3921718862457,
      "defense": 370.78537462399254,
      "specialized": 0
    },
    "s40p": {
      "level": 40,
      "ascension": 2,
      "hp": 5559.1502890923875,
      "attack": 129.00341036585996,
      "defense": 414.52537630245934,
      "specialized": 0.055399999022483826
    },
    "s50": {
      "level": 50,
      "ascension": 2,
      "hp": 6395.86968856983,
      "attack": 148.42034530892943,
      "defense": 476.9160952212369,
      "specialized": 0.055399999022483826
    },
    "s50p": {
      "level": 50,
      "ascension": 3,
      "hp": 7177.978819429205,
      "attack": 166.5686645533142,
      "defense": 535.2360872866666,
      "specialized": 0.11079999804496765
    },
    "s60": {
      "level": 60,
      "ascension": 3,
      "hp": 8023.363728842989,
      "attack": 186.18669157431032,
      "defense": 598.272957585541,
      "specialized": 0.11079999804496765
    },
    "s60p": {
      "level": 60,
      "ascension": 4,
      "hp": 8609.945515952364,
      "attack": 199.7979319612732,
      "defense": 642.0129630787051,
      "specialized": 0.11079999804496765
    },
    "s70": {
      "level": 70,
      "ascension": 4,
      "hp": 9463.033611003106,
      "attack": 219.59471933425903,
      "defense": 705.6242281987761,
      "specialized": 0.11079999804496765
    },
    "s70p": {
      "level": 70,
      "ascension": 5,
      "hp": 10049.61539811248,
      "attack": 233.20596353591918,
      "defense": 749.3642336919402,
      "specialized": 0.16619999706745148
    },
    "s80": {
      "level": 80,
      "ascension": 5,
      "hp": 10912.331786523137,
      "attack": 253.22618536721802,
      "defense": 813.6934409860078,
      "specialized": 0.16619999706745148
    },
    "s80p": {
      "level": 80,
      "ascension": 6,
      "hp": 11498.913573632512,
      "attack": 266.83742193948365,
      "defense": 857.4334312203828,
      "specialized": 0.2214999943971634
    },
    "s90": {
      "level": 90,
      "ascension": 6,
      "hp": 12368.370364256552,
      "attack": 287.0140617423858,
      "defense": 922.2652425417473,
      "specialized": 0.2214999943971634
    }
  },
  "version": "1.0",
  "constellations": {
    "c1": {
      "name": "한고의 회향",
      "effect": "한병의 귀차의 공격이 도액 부적 표식이 있는 적을 명중 시 치치의 원소 에너지를 2pt 회복한다"
    },
    "c2": {
      "name": "뼛속까지 스며드는 한기",
      "effect": "얼음 원소의 영향을 받은 적을 공격 시 치치가 일반 공격과 강공격으로 가하는 피해가 15% 증가한다"
    },
    "c3": {
      "name": "승천 보고(宝诰)",
      "effect": "**선법·구고도액**의 스킬 레벨+3\n최대 Lv.15까지 상승"
    },
    "c4": {
      "name": "중생을 압도하는 천위",
      "effect": "도액 부적 표식이 있는 적은 공격력이 20% 감소한다"
    },
    "c5": {
      "name": "피어난 홍련",
      "effect": "**선법·한병의 귀차**의 스킬 레벨+3\n최대 Lv.15까지 상승"
    },
    "c6": {
      "name": "기사회해",
      "effect": "**선법·구고도액** 발동 시 근처 파티 내 전투 불능이 된 모든 캐릭터를 부활시키고 HP를 50% 회복한다.\n해당 효과는 15분마다 1회만 발동한다"
    },
    "images": {
      "c1": "https://upload-os-bbs.mihoyo.com/game_record/genshin/constellation_icon/UI_Talent_S_Qiqi_01.png",
      "c2": "https://upload-os-bbs.mihoyo.com/game_record/genshin/constellation_icon/UI_Talent_S_Qiqi_02.png",
      "c3": "https://upload-os-bbs.mihoyo.com/game_record/genshin/constellation_icon/UI_Talent_U_Qiqi_01.png",
      "c4": "https://upload-os-bbs.mihoyo.com/game_record/genshin/constellation_icon/UI_Talent_S_Qiqi_03.png",
      "c5": "https://upload-os-bbs.mihoyo.com/game_record/genshin/constellation_icon/UI_Talent_U_Qiqi_02.png",
      "c6": "https://upload-os-bbs.mihoyo.com/game_record/genshin/constellation_icon/UI_Talent_S_Qiqi_04.png",
      "constellation": "Eff_UI_Talent_Qiqi"
    },
    "version": "1.0"
  },
  "talent": {
    "name": "치치",
    "combat1": {
      "name": "일반 공격·운래의 고대 검법",
      "info": "**일반 공격**\n검으로 최대 5번 공격한다.\n\n**강공격**\n일정 스태미나를 소모해 순간적으로 전방을 향해 검을 2번 휘두른다.\n\n**낙하 공격**\n공중에서 땅을 내려찍어 경로상의 적을 공격하고, 착지 시 범위 피해를 준다",
      "attributes": [
        {
          "name": "1단 공격 피해",
          "parameters": [
            "37.75%",
            "40.83%",
            "43.90%",
            "48.29%",
            "51.36%",
            "54.87%",
            "59.70%",
            "64.53%",
            "69.36%",
            "74.63%",
            "79.90%",
            "85.17%",
            "90.43%",
            "95.70%",
            "100.97%"
          ]
        },
        {
          "name": "2단 공격 피해",
          "parameters": [
            "38.87%",
            "42.04%",
            "45.20%",
            "49.72%",
            "52.88%",
            "56.50%",
            "61.47%",
            "66.44%",
            "71.42%",
            "76.84%",
            "82.26%",
            "87.69%",
            "93.11%",
            "98.54%",
            "103.96%"
          ]
        },
        {
          "name": "3단 공격 피해",
          "parameters": [
            "24.17%+24.17%",
            "26.13%+26.13%",
            "28.10%+28.10%",
            "30.91%+30.91%",
            "32.88%+32.88%",
            "35.12%+35.12%",
            "38.22%+38.22%",
            "41.31%+41.31%",
            "44.40%+44.40%",
            "47.77%+47.77%",
            "51.14%+51.14%",
            "54.51%+54.51%",
            "57.89%+57.89%",
            "61.26%+61.26%",
            "64.63%+64.63%"
          ]
        },
        {
          "name": "4단 공격 피해",
          "parameters": [
            "24.68%+24.68%",
            "26.69%+26.69%",
            "28.70%+28.70%",
            "31.57%+31.57%",
            "33.58%+33.58%",
            "35.87%+35.87%",
            "39.03%+39.03%",
            "42.19%+42.19%",
            "45.35%+45.35%",
            "48.79%+48.79%",
            "52.23%+52.23%",
            "55.68%+55.68%",
            "59.12%+59.12%",
            "62.57%+62.57%",
            "66.01%+66.01%"
          ]
        },
        {
          "name": "5단 공격 피해",
          "parameters": [
            "63.04%",
            "68.17%",
            "73.30%",
            "80.63%",
            "85.76%",
            "91.62%",
            "99.69%",
            "107.75%",
            "115.81%",
            "124.61%",
            "133.41%",
            "142.20%",
            "151.00%",
            "159.79%",
            "168.59%"
          ]
        },
        {
          "name": "강공격 피해",
          "parameters": [
            "64.33%+64.33%",
            "69.56%+69.56%",
            "74.80%+74.80%",
            "82.28%+82.28%",
            "87.52%+87.52%",
            "93.50%+93.50%",
            "101.73%+101.73%",
            "109.96%+109.96%",
            "118.18%+118.18%",
            "127.16%+127.16%",
            "136.14%+136.14%",
            "145.11%+145.11%",
            "154.09%+154.09%",
            "163.06%+163.06%",
            "172.04%+172.04%"
          ]
        },
        {
          "name": "강공격 스태미나 소모",
          "parameters": [
            "20pt",
            "20pt",
            "20pt",
            "20pt",
            "20pt",
            "20pt",
            "20pt",
            "20pt",
            "20pt",
            "20pt",
            "20pt",
            "20pt",
            "20pt",
            "20pt",
            "20pt"
          ]
        },
        {
          "name": "낙하 기간 피해",
          "parameters": [
            "63.93%",
            "69.14%",
            "74.34%",
            "81.77%",
            "86.98%",
            "92.93%",
            "101.10%",
            "109.28%",
            "117.46%",
            "126.38%",
            "135.30%",
            "144.22%",
            "153.14%",
            "162.06%",
            "170.98%"
          ]
        },
        {
          "name": "저공/고공 추락 충격 피해",
          "parameters": [
            "127.84%/159.68%",
            "138.24%/172.67%",
            "148.65%/185.67%",
            "163.51%/204.24%",
            "173.92%/217.23%",
            "185.81%/232.09%",
            "202.16%/252.51%",
            "218.51%/272.93%",
            "234.86%/293.36%",
            "252.70%/315.64%",
            "270.54%/337.92%",
            "288.38%/360.20%",
            "306.22%/382.48%",
            "324.05%/404.76%",
            "341.89%/427.04%"
          ]
        }
      ]
    },
    "combat2": {
      "name": "선법·한병의 귀차",
      "info": "얼음과 피로 만들어진 부적으로 한병의 귀차를 소환해 주변의 적에게 얼음 원소 피해를 준다.\n\n**한병의 귀차**\n·치치의 일반 공격과 강공격이 명중 시 자신의 파티 내 모든 캐릭터 및 근처 아군 캐릭터의 HP를 회복한다. 회복량은 치치의 공격력의 영향을 받는다.\n·일정 시간이 지날 때마다 현재 필드 위에 있는 자신의 캐릭터의 HP를 회복한다.\n·캐릭터를 따라다니며 경로상의 적에게 얼음 원소 피해를 준다.",
      "description": "「얘는 주로 온도가 올라서 부패하는 걸 방지해줘요…. 음, 그러니까 백 선생님의 진귀한 약재들 말이에요」",
      "attributes": [
        {
          "name": "스킬 피해",
          "parameters": [
            "96.00%",
            "103.20%",
            "110.40%",
            "120.00%",
            "127.20%",
            "134.40%",
            "144.00%",
            "153.60%",
            "163.20%",
            "172.80%",
            "182.40%",
            "192.00%",
            "204.00%",
            "216.00%",
            "228.00%"
          ]
        },
        {
          "name": "명중 치유량",
          "parameters": [
            "공격력의 10.56%+67",
            "공격력의 11.35%+74",
            "공격력의 12.14%+81",
            "공격력의 13.20%+89",
            "공격력의 13.99%+98",
            "공격력의 14.78%+107",
            "공격력의 15.84%+116",
            "공격력의 16.90%+126",
            "공격력의 17.95%+137",
            "공격력의 19.01%+148",
            "공격력의 20.06%+160",
            "공격력의 21.12%+172",
            "공격력의 22.44%+185",
            "공격력의 23.76%+199",
            "공격력의 25.08%+213"
          ]
        },
        {
          "name": "지속 치유량",
          "parameters": [
            "공격력의 69.60%+451",
            "공격력의 74.82%+496",
            "공격력의 80.04%+544",
            "공격력의 87.00%+597",
            "공격력의 92.22%+653",
            "공격력의 97.44%+713",
            "공격력의 104.40%+777",
            "공격력의 111.36%+845",
            "공격력의 118.32%+916",
            "공격력의 125.28%+991",
            "공격력의 132.24%+1070",
            "공격력의 139.20%+1153",
            "공격력의 147.90%+1239",
            "공격력의 156.60%+1329",
            "공격력의 165.30%+1423"
          ]
        },
        {
          "name": "한병의 귀차 피해",
          "parameters": [
            "36.00%",
            "38.70%",
            "41.40%",
            "45.00%",
            "47.70%",
            "50.40%",
            "54.00%",
            "57.60%",
            "61.20%",
            "64.80%",
            "68.40%",
            "72.00%",
            "76.50%",
            "81.00%",
            "85.50%"
          ]
        },
        {
          "name": "지속 시간",
          "parameters": [
            "15초",
            "15초",
            "15초",
            "15초",
            "15초",
            "15초",
            "15초",
            "15초",
            "15초",
            "15초",
            "15초",
            "15초",
            "15초",
            "15초",
            "15초"
          ]
        },
        {
          "name": "재사용 대기시간",
          "parameters": [
            "30초",
            "30초",
            "30초",
            "30초",
            "30초",
            "30초",
            "30초",
            "30초",
            "30초",
            "30초",
            "30초",
            "30초",
            "30초",
            "30초",
            "30초"
          ]
        }
      ]
    },
    "combat3": {
      "name": "선법·구고도액",
      "info": "치치가 체내에 봉인된 선력을 해방해 주변의 적에게 도액 부적 표식을 남기고 얼음 원소 피해를 준다.\n\n**도액 부적**\n도액 부적 표식이 있는 적에게 피해를 주면 캐릭터의 HP를 회복한다.",
      "description": "「본명, 구고도액진군. 죽다 살아난 해골 동자」\n——치치는 이 말을 기억하지 못한다",
      "attributes": [
        {
          "name": "스킬 피해",
          "parameters": [
            "284.80%",
            "306.16%",
            "327.52%",
            "356.00%",
            "377.36%",
            "398.72%",
            "427.20%",
            "455.68%",
            "484.16%",
            "512.64%",
            "541.12%",
            "569.60%",
            "605.20%",
            "640.80%",
            "676.40%"
          ]
        },
        {
          "name": "치유량",
          "parameters": [
            "공격력의 90.00%+577",
            "공격력의 96.75%+635",
            "공격력의 103.50%+698",
            "공격력의 112.50%+765",
            "공격력의 119.25%+837",
            "공격력의 126.00%+914",
            "공격력의 135.00%+996",
            "공격력의 144.00%+1083",
            "공격력의 153.00%+1174",
            "공격력의 162.00%+1270",
            "공격력의 171.00%+1371",
            "공격력의 180.00%+1477",
            "공격력의 191.25%+1588",
            "공격력의 202.50%+1703",
            "공격력의 213.75%+1824"
          ]
        },
        {
          "name": "지속 시간",
          "parameters": [
            "15초",
            "15초",
            "15초",
            "15초",
            "15초",
            "15초",
            "15초",
            "15초",
            "15초",
            "15초",
            "15초",
            "15초",
            "15초",
            "15초",
            "15초"
          ]
        },
        {
          "name": "재사용 대기시간",
          "parameters": [
            "20초",
            "20초",
            "20초",
            "20초",
            "20초",
            "20초",
            "20초",
            "20초",
            "20초",
            "20초",
            "20초",
            "20초",
            "20초",
            "20초",
            "20초"
          ]
        },
        {
          "name": "원소 에너지",
          "parameters": [
            "80",
            "80",
            "80",
            "80",
            "80",
            "80",
            "80",
            "80",
            "80",
            "80",
            "80",
            "80",
            "80",
            "80",
            "80"
          ]
        }
      ]
    },
    "passive1": {
      "name": "생명 연장의 묘법",
      "info": "**선법·한병의 귀차** 상태의 캐릭터가 원소 반응을 일으키면 받는 치유 보너스가 20% 상승한다. 지속 시간: 8초"
    },
    "passive2": {
      "name": "우연히 얻은 옥첨",
      "info": "치치의 일반 공격과 강공격이 적을 명중 시 50%의 확률로 적에게 도액 부적을 한 장 부여한다. 지속 시간: 6초. 해당 효과는 30초마다 1회만 발동한다"
    },
    "passive3": {
      "name": "지나간 기억",
      "info": "미니맵에 주위의 **리월 지역 특산물** 위치가 나타난다"
    },
    "costs": {
      "lvl2": [
        {
          "name": "모라",
          "count": 12500
        },
        {
          "name": "「번영」의 가르침",
          "count": 3
        },
        {
          "name": "이능 두루마리",
          "count": 6
        }
      ],
      "lvl3": [
        {
          "name": "모라",
          "count": 17500
        },
        {
          "name": "「번영」의 인도",
          "count": 2
        },
        {
          "name": "봉마의 두루마리",
          "count": 3
        }
      ],
      "lvl4": [
        {
          "name": "모라",
          "count": 25000
        },
        {
          "name": "「번영」의 인도",
          "count": 4
        },
        {
          "name": "봉마의 두루마리",
          "count": 4
        }
      ],
      "lvl5": [
        {
          "name": "모라",
          "count": 30000
        },
        {
          "name": "「번영」의 인도",
          "count": 6
        },
        {
          "name": "봉마의 두루마리",
          "count": 6
        }
      ],
      "lvl6": [
        {
          "name": "모라",
          "count": 37500
        },
        {
          "name": "「번영」의 인도",
          "count": 9
        },
        {
          "name": "봉마의 두루마리",
          "count": 9
        }
      ],
      "lvl7": [
        {
          "name": "모라",
          "count": 120000
        },
        {
          "name": "「번영」의 철학",
          "count": 4
        },
        {
          "name": "금주의 두루마리",
          "count": 4
        },
        {
          "name": "북풍의 꼬리",
          "count": 1
        }
      ],
      "lvl8": [
        {
          "name": "모라",
          "count": 260000
        },
        {
          "name": "「번영」의 철학",
          "count": 6
        },
        {
          "name": "금주의 두루마리",
          "count": 6
        },
        {
          "name": "북풍의 꼬리",
          "count": 1
        }
      ],
      "lvl9": [
        {
          "name": "모라",
          "count": 450000
        },
        {
          "name": "「번영」의 철학",
          "count": 12
        },
        {
          "name": "금주의 두루마리",
          "count": 9
        },
        {
          "name": "북풍의 꼬리",
          "count": 2
        }
      ],
      "lvl10": [
        {
          "name": "모라",
          "count": 700000
        },
        {
          "name": "「번영」의 철학",
          "count": 16
        },
        {
          "name": "금주의 두루마리",
          "count": 12
        },
        {
          "name": "북풍의 꼬리",
          "count": 2
        },
        {
          "name": "지식의 왕관",
          "count": 1
        }
      ]
    },
    "images": {
      "combat1": "Skill_A_01",
      "combat2": "Skill_S_Qiqi_01",
      "combat3": "Skill_E_Qiqi_01_HD",
      "passive1": "UI_Talent_S_Qiqi_05",
      "passive2": "UI_Talent_S_Qiqi_06",
      "passive3": "UI_Talent_Collect_Local_Liyue"
    },
    "version": "1.0"
  }
}