{
  "name": "Hunting Trap",
  "description": "ใช้ดักจับสัตว์อสูรขนาดประมาณนึงได้ หากคุณตั้งใจหาพวกมันในป่า มันก็ยังพอจะสามารถนำมาทำเป็นกับดักแบบนี้ได้ ตั้งไว้อันนึงและหลบซ่อนไว้ให้ดี",
  "sortorder": 99,
  "category": "CONSUME",
  "materialtype": "วัสดุใช้งาน",
  "source": [],
  "images": {
    "nameicon": "UI_ItemIcon_100225",
    "redirect": "https://genshin-impact.fandom.com/wiki/Special:Redirect/file/Item_Hunting_Trap.png",
    "fandom": "https://static.wikia.nocookie.net/gensin-impact/images/8/84/Item_Hunting_Trap.png"
  },
  "url": {
    "fandom": "https://genshin-impact.fandom.com/wiki/Hunting_Trap"
  },
  "version": ""
}