{
  "name": "重雲",
  "fullname": "重雲",
  "title": "雪融有蹤",
  "description": "驅邪世家的年輕術士，為壓制自身的「純陽之體」費盡心機。",
  "rarity": "4",
  "element": "冰",
  "weapontype": "雙手劍",
  "substat": "攻擊力",
  "gender": "男",
  "body": "BOY",
  "association": "LIYUE",
  "region": "Liyue",
  "affiliation": "天衡方士",
  "birthdaymmdd": "9/7",
  "birthday": "9月7日",
  "constellation": "乾坤鋒座",
  "cv": {
    "english": "Beau Bridgland",
    "chinese": "kinsen",
    "japanese": "斉藤壮馬",
    "korean": "梁靜花"
  },
  "costs": {
    "ascend1": [
      {
        "name": "摩拉",
        "count": 20000
      },
      {
        "name": "哀敘冰玉碎屑",
        "count": 1
      },
      {
        "name": "石珀",
        "count": 3
      },
      {
        "name": "破損的面具",
        "count": 3
      }
    ],
    "ascend2": [
      {
        "name": "摩拉",
        "count": 40000
      },
      {
        "name": "哀敘冰玉斷片",
        "count": 3
      },
      {
        "name": "極寒之核",
        "count": 2
      },
      {
        "name": "石珀",
        "count": 10
      },
      {
        "name": "破損的面具",
        "count": 15
      }
    ],
    "ascend3": [
      {
        "name": "摩拉",
        "count": 60000
      },
      {
        "name": "哀敘冰玉斷片",
        "count": 6
      },
      {
        "name": "極寒之核",
        "count": 4
      },
      {
        "name": "石珀",
        "count": 20
      },
      {
        "name": "汙穢的面具",
        "count": 12
      }
    ],
    "ascend4": [
      {
        "name": "摩拉",
        "count": 80000
      },
      {
        "name": "哀敘冰玉塊",
        "count": 3
      },
      {
        "name": "極寒之核",
        "count": 8
      },
      {
        "name": "石珀",
        "count": 30
      },
      {
        "name": "汙穢的面具",
        "count": 18
      }
    ],
    "ascend5": [
      {
        "name": "摩拉",
        "count": 100000
      },
      {
        "name": "哀敘冰玉塊",
        "count": 6
      },
      {
        "name": "極寒之核",
        "count": 12
      },
      {
        "name": "石珀",
        "count": 45
      },
      {
        "name": "不祥的面具",
        "count": 12
      }
    ],
    "ascend6": [
      {
        "name": "摩拉",
        "count": 120000
      },
      {
        "name": "哀敘冰玉",
        "count": 6
      },
      {
        "name": "極寒之核",
        "count": 20
      },
      {
        "name": "石珀",
        "count": 60
      },
      {
        "name": "不祥的面具",
        "count": 24
      }
    ]
  },
  "images": {
    "card": "https://static.wikia.nocookie.net/gensin-impact/images/f/fa/Character_Chongyun_Card.jpg",
    "portrait": "https://static.wikia.nocookie.net/gensin-impact/images/a/aa/Character_Chongyun_Portrait.png",
    "icon": "https://upload-os-bbs.mihoyo.com/game_record/genshin/character_icon/UI_AvatarIcon_Chongyun.png",
    "sideicon": "https://upload-os-bbs.mihoyo.com/game_record/genshin/character_side_icon/UI_AvatarIcon_Side_Chongyun.png",
    "cover1": "https://uploadstatic-sea.hoyoverse.com/contentweb/20200602/2020060220172055224.png",
    "cover2": "https://uploadstatic-sea.hoyoverse.com/contentweb/20200602/2020060220205013044.png",
    "hoyolab-avatar": "https://img-os-static.hoyolab.com/communityWeb/upload/af335b6e68883e7e40237040aa020cf1.png",
    "nameicon": "UI_AvatarIcon_Chongyun",
    "nameiconcard": "UI_AvatarIcon_Chongyun_Card",
    "namegachasplash": "UI_Gacha_AvatarImg_Chongyun",
    "namegachaslice": "UI_Gacha_AvatarIcon_Chongyun",
    "namesideicon": "UI_AvatarIcon_Side_Chongyun"
  },
  "url": {
    "fandom": "https://genshin-impact.fandom.com/wiki/Chongyun"
  },
  "stats": {
    "s1": {
      "level": 1,
      "ascension": 0,
      "hp": 920.908935546875,
      "attack": 18.698400497436523,
      "defense": 54.36375045776367,
      "specialized": 0
    },
    "s20": {
      "level": 20,
      "ascension": 0,
      "hp": 2365.815060689405,
      "attack": 48.036190984907535,
      "defense": 139.66047523706675,
      "specialized": 0
    },
    "s20p": {
      "level": 20,
      "ascension": 1,
      "hp": 3053.7811861776863,
      "attack": 62.00518131083527,
      "defense": 180.2729744741273,
      "specialized": 0
    },
    "s40": {
      "level": 40,
      "ascension": 1,
      "hp": 4574.20164028171,
      "attack": 92.87623650202931,
      "defense": 270.0275147628545,
      "specialized": 0
    },
    "s40p": {
      "level": 40,
      "ascension": 2,
      "hp": 5063.019694480929,
      "attack": 102.80157143244924,
      "defense": 298.88376552579393,
      "specialized": 0.05999999865889549
    },
    "s50": {
      "level": 50,
      "ascension": 2,
      "hp": 5823.69067197002,
      "attack": 118.24645423774109,
      "defense": 343.78823501725674,
      "specialized": 0.05999999865889549
    },
    "s50p": {
      "level": 50,
      "ascension": 3,
      "hp": 6475.44799618877,
      "attack": 131.48023414496765,
      "defense": 382.26323349137783,
      "specialized": 0.11999999731779099
    },
    "s60": {
      "level": 60,
      "ascension": 3,
      "hp": 7236.1189736778615,
      "attack": 146.9251169502595,
      "defense": 427.16770298284064,
      "specialized": 0.11999999731779099
    },
    "s60p": {
      "level": 60,
      "ascension": 4,
      "hp": 7724.9370889122365,
      "attack": 156.85045188067943,
      "defense": 456.02395756047736,
      "specialized": 0.11999999731779099
    },
    "s70": {
      "level": 70,
      "ascension": 4,
      "hp": 8484.686785088968,
      "attack": 172.2766287246277,
      "defense": 500.8740413190699,
      "specialized": 0.11999999731779099
    },
    "s70p": {
      "level": 70,
      "ascension": 5,
      "hp": 8973.504656182718,
      "attack": 182.20196365504762,
      "defense": 529.7302882673121,
      "specialized": 0.18000000715255737
    },
    "s80": {
      "level": 80,
      "ascension": 5,
      "hp": 9734.17519454821,
      "attack": 197.64683754424732,
      "defense": 574.6347318361186,
      "specialized": 0.18000000715255737
    },
    "s80p": {
      "level": 80,
      "ascension": 6,
      "hp": 10222.993309782585,
      "attack": 207.5721762893645,
      "defense": 603.4909787843608,
      "specialized": 0.23999999463558197
    },
    "s90": {
      "level": 90,
      "ascension": 6,
      "hp": 10983.664287271677,
      "attack": 223.01705909465636,
      "defense": 648.3954482758236,
      "specialized": 0.23999999463558197
    }
  },
  "version": "1.0",
  "constellations": {
    "c1": {
      "name": "釋淩詠冰",
      "effect": "普通攻擊的最後一擊會向前方釋放三道冰之刃，每道冰之刃對沿途的敵人造成重雲50%攻擊力的冰元素傷害。"
    },
    "c2": {
      "name": "周天運轉",
      "effect": "在**靈刃·重華疊霜**領域內施放的元素戰技與元素爆發的冷卻時間減少15%。"
    },
    "c3": {
      "name": "雲盡光生",
      "effect": "**靈刃·雲開星落**的技能等級提高3級。\n至多提升至15級。"
    },
    "c4": {
      "name": "浮雲霜天",
      "effect": "重雲的所有攻擊命中受到冰元素影響的敵人時，自身將恢復1點元素能量。\n該效果每2秒最多觸發一次。"
    },
    "c5": {
      "name": "真道正理",
      "effect": "**靈刃·重華疊霜**的技能等級提高3級。\n至多提升至15級。"
    },
    "c6": {
      "name": "四靈捧聖",
      "effect": "**靈刃·雲開星落**對生命值百分比低於重雲的敵人造成傷害時，傷害提升15%；\n此外，施放時，會召喚一柄額外的靈刃。"
    },
    "images": {
      "c1": "https://upload-os-bbs.mihoyo.com/game_record/genshin/constellation_icon/UI_Talent_S_Chongyun_01.png",
      "c2": "https://upload-os-bbs.mihoyo.com/game_record/genshin/constellation_icon/UI_Talent_S_Chongyun_02.png",
      "c3": "https://upload-os-bbs.mihoyo.com/game_record/genshin/constellation_icon/UI_Talent_U_Chongyun_01.png",
      "c4": "https://upload-os-bbs.mihoyo.com/game_record/genshin/constellation_icon/UI_Talent_S_Chongyun_03.png",
      "c5": "https://upload-os-bbs.mihoyo.com/game_record/genshin/constellation_icon/UI_Talent_U_Chongyun_02.png",
      "c6": "https://upload-os-bbs.mihoyo.com/game_record/genshin/constellation_icon/UI_Talent_S_Chongyun_04.png",
      "constellation": "Eff_UI_Talent_Chongyun"
    },
    "version": "1.0"
  },
  "talent": {
    "name": "重雲",
    "combat1": {
      "name": "普通攻擊·滅邪四式",
      "info": "**普通攻擊**\n進行至多四段的連續揮砍。\n\n**重擊**\n持續消耗體力，旋轉大劍攻擊周圍的敵人。\n停止旋轉時，會進行一次格外有力的揮砍。\n\n**下落攻擊**\n從空中下墜衝擊地面，攻擊下落路徑上的敵人，並在落地時造成範圍傷害。",
      "attributes": [
        {
          "name": "一段傷害",
          "parameters": [
            "70.00%",
            "75.70%",
            "81.40%",
            "89.54%",
            "95.24%",
            "101.75%",
            "110.70%",
            "119.66%",
            "128.61%",
            "138.38%",
            "148.15%",
            "157.92%",
            "167.68%",
            "177.45%",
            "187.22%"
          ]
        },
        {
          "name": "二段傷害",
          "parameters": [
            "63.12%",
            "68.26%",
            "73.40%",
            "80.74%",
            "85.88%",
            "91.75%",
            "99.82%",
            "107.90%",
            "115.97%",
            "124.78%",
            "133.59%",
            "142.40%",
            "151.20%",
            "160.01%",
            "168.82%"
          ]
        },
        {
          "name": "三段傷害",
          "parameters": [
            "80.32%",
            "86.86%",
            "93.40%",
            "102.74%",
            "109.28%",
            "116.75%",
            "127.02%",
            "137.30%",
            "147.57%",
            "158.78%",
            "169.99%",
            "181.20%",
            "192.40%",
            "203.61%",
            "214.82%"
          ]
        },
        {
          "name": "四段傷害",
          "parameters": [
            "101.22%",
            "109.46%",
            "117.70%",
            "129.47%",
            "137.71%",
            "147.13%",
            "160.07%",
            "173.02%",
            "185.97%",
            "200.09%",
            "214.21%",
            "228.34%",
            "242.46%",
            "256.59%",
            "270.71%"
          ]
        },
        {
          "name": "重擊循環傷害",
          "parameters": [
            "56.29%",
            "60.87%",
            "65.45%",
            "71.99%",
            "76.57%",
            "81.81%",
            "89.01%",
            "96.21%",
            "103.41%",
            "111.26%",
            "119.12%",
            "126.97%",
            "134.82%",
            "142.68%",
            "150.53%"
          ]
        },
        {
          "name": "重擊終結傷害",
          "parameters": [
            "101.78%",
            "110.07%",
            "118.35%",
            "130.18%",
            "138.47%",
            "147.94%",
            "160.96%",
            "173.97%",
            "186.99%",
            "201.20%",
            "215.40%",
            "229.60%",
            "243.80%",
            "258.00%",
            "272.20%"
          ]
        },
        {
          "name": "重擊體力消耗",
          "parameters": [
            "每秒40點",
            "每秒40點",
            "每秒40點",
            "每秒40點",
            "每秒40點",
            "每秒40點",
            "每秒40點",
            "每秒40點",
            "每秒40點",
            "每秒40點",
            "每秒40點",
            "每秒40點",
            "每秒40點",
            "每秒40點",
            "每秒40點"
          ]
        },
        {
          "name": "最大持續時間",
          "parameters": [
            "5秒",
            "5秒",
            "5秒",
            "5秒",
            "5秒",
            "5秒",
            "5秒",
            "5秒",
            "5秒",
            "5秒",
            "5秒",
            "5秒",
            "5秒",
            "5秒",
            "5秒"
          ]
        },
        {
          "name": "下墜期間傷害",
          "parameters": [
            "74.59%",
            "80.66%",
            "86.73%",
            "95.40%",
            "101.47%",
            "108.41%",
            "117.95%",
            "127.49%",
            "137.03%",
            "147.44%",
            "157.85%",
            "168.26%",
            "178.66%",
            "189.07%",
            "199.48%"
          ]
        },
        {
          "name": "低空/高空墜地衝擊傷害",
          "parameters": [
            "149.14%/186.29%",
            "161.28%/201.45%",
            "173.42%/216.62%",
            "190.77%/238.28%",
            "202.91%/253.44%",
            "216.78%/270.77%",
            "235.86%/294.60%",
            "254.93%/318.42%",
            "274.01%/342.25%",
            "294.82%/368.25%",
            "315.63%/394.24%",
            "336.44%/420.23%",
            "357.25%/446.23%",
            "378.06%/472.22%",
            "398.87%/498.21%"
          ]
        }
      ]
    },
    "combat2": {
      "name": "靈刃·重華疊霜",
      "info": "重雲揮動巨劍猛擊地面，在前方圓形範圍內引發冰爆，並對敵人造成冰元素傷害。\n短暫延遲後，冰爆引發的寒氣彙聚成重華疊霜領域，其中的單手劍、大劍、長柄武器角色獲得冰元素附魔。",
      "description": "「琳琅振響，十方靜默。江河不動，重雲凝霜。如法開壇，諸邪退散。」",
      "attributes": [
        {
          "name": "技能傷害",
          "parameters": [
            "172.04%",
            "184.94%",
            "197.85%",
            "215.05%",
            "227.95%",
            "240.86%",
            "258.06%",
            "275.26%",
            "292.47%",
            "309.67%",
            "326.88%",
            "344.08%",
            "365.58%",
            "387.09%",
            "408.59%"
          ]
        },
        {
          "name": "附魔持續時間",
          "parameters": [
            "2秒",
            "2.0999999046325684秒",
            "2.200000047683716秒",
            "2.299999952316284秒",
            "2.4000000953674316秒",
            "2.5秒",
            "2.5999999046325684秒",
            "2.700000047683716秒",
            "2.799999952316284秒",
            "2.9000000953674316秒",
            "3秒",
            "3秒",
            "3秒",
            "3秒",
            "3秒"
          ]
        },
        {
          "name": "領域持續時間",
          "parameters": [
            "10秒",
            "10秒",
            "10秒",
            "10秒",
            "10秒",
            "10秒",
            "10秒",
            "10秒",
            "10秒",
            "10秒",
            "10秒",
            "10秒",
            "10秒",
            "10秒",
            "10秒"
          ]
        },
        {
          "name": "冷卻時間",
          "parameters": [
            "15秒",
            "15秒",
            "15秒",
            "15秒",
            "15秒",
            "15秒",
            "15秒",
            "15秒",
            "15秒",
            "15秒",
            "15秒",
            "15秒",
            "15秒",
            "15秒",
            "15秒"
          ]
        }
      ]
    },
    "combat3": {
      "name": "靈刃·雲開星落",
      "info": "重雲結印，在前方半空中連續召喚出三柄巨大靈刃，短時間內依次落向地面並爆裂。\n靈刃爆裂時，會造成冰元素範圍傷害，並擊飛敵人。",
      "description": "「卓劍天地動，冰淩霜寒生。如律令！」",
      "attributes": [
        {
          "name": "技能傷害",
          "parameters": [
            "142.40%",
            "153.08%",
            "163.76%",
            "178.00%",
            "188.68%",
            "199.36%",
            "213.60%",
            "227.84%",
            "242.08%",
            "256.32%",
            "270.56%",
            "284.80%",
            "302.60%",
            "320.40%",
            "338.20%"
          ]
        },
        {
          "name": "冷卻時間",
          "parameters": [
            "12秒",
            "12秒",
            "12秒",
            "12秒",
            "12秒",
            "12秒",
            "12秒",
            "12秒",
            "12秒",
            "12秒",
            "12秒",
            "12秒",
            "12秒",
            "12秒",
            "12秒"
          ]
        },
        {
          "name": "元素能量",
          "parameters": [
            "40",
            "40",
            "40",
            "40",
            "40",
            "40",
            "40",
            "40",
            "40",
            "40",
            "40",
            "40",
            "40",
            "40",
            "40"
          ]
        }
      ]
    },
    "passive1": {
      "name": "吐納真定",
      "info": "處在**靈刃·重華疊霜**領域內的單手劍、雙手劍、長柄武器角色，普通攻擊的攻擊速度提升8%。"
    },
    "passive2": {
      "name": "追冰劍訣",
      "info": "**靈刃·重華疊霜**領域消失時，會喚出一柄靈刃自動攻擊附近的敵人，造成相當於靈刃·重華疊霜技能傷害100%的冰元素範圍傷害。被擊中的敵人冰元素抗性降低10%，持續8秒。"
    },
    "passive3": {
      "name": "雲遊山海",
      "info": "在璃月執行探索派遣任務時，消耗的時間縮短25%。"
    },
    "costs": {
      "lvl2": [
        {
          "name": "摩拉",
          "count": 12500
        },
        {
          "name": "「勤勞」的教導",
          "count": 3
        },
        {
          "name": "破損的面具",
          "count": 6
        }
      ],
      "lvl3": [
        {
          "name": "摩拉",
          "count": 17500
        },
        {
          "name": "「勤勞」的指引",
          "count": 2
        },
        {
          "name": "汙穢的面具",
          "count": 3
        }
      ],
      "lvl4": [
        {
          "name": "摩拉",
          "count": 25000
        },
        {
          "name": "「勤勞」的指引",
          "count": 4
        },
        {
          "name": "汙穢的面具",
          "count": 4
        }
      ],
      "lvl5": [
        {
          "name": "摩拉",
          "count": 30000
        },
        {
          "name": "「勤勞」的指引",
          "count": 6
        },
        {
          "name": "汙穢的面具",
          "count": 6
        }
      ],
      "lvl6": [
        {
          "name": "摩拉",
          "count": 37500
        },
        {
          "name": "「勤勞」的指引",
          "count": 9
        },
        {
          "name": "汙穢的面具",
          "count": 9
        }
      ],
      "lvl7": [
        {
          "name": "摩拉",
          "count": 120000
        },
        {
          "name": "「勤勞」的哲學",
          "count": 4
        },
        {
          "name": "不祥的面具",
          "count": 4
        },
        {
          "name": "東風的吐息",
          "count": 1
        }
      ],
      "lvl8": [
        {
          "name": "摩拉",
          "count": 260000
        },
        {
          "name": "「勤勞」的哲學",
          "count": 6
        },
        {
          "name": "不祥的面具",
          "count": 6
        },
        {
          "name": "東風的吐息",
          "count": 1
        }
      ],
      "lvl9": [
        {
          "name": "摩拉",
          "count": 450000
        },
        {
          "name": "「勤勞」的哲學",
          "count": 12
        },
        {
          "name": "不祥的面具",
          "count": 9
        },
        {
          "name": "東風的吐息",
          "count": 2
        }
      ],
      "lvl10": [
        {
          "name": "摩拉",
          "count": 700000
        },
        {
          "name": "「勤勞」的哲學",
          "count": 16
        },
        {
          "name": "不祥的面具",
          "count": 12
        },
        {
          "name": "東風的吐息",
          "count": 2
        },
        {
          "name": "智識之冕",
          "count": 1
        }
      ]
    },
    "images": {
      "combat1": "Skill_A_04",
      "combat2": "Skill_S_Chongyun_01",
      "combat3": "Skill_E_Chongyun_01_HD",
      "passive1": "UI_Talent_S_Chongyun_05",
      "passive2": "UI_Talent_S_Chongyun_06",
      "passive3": "UI_Talent_Expedition_Liyue"
    },
    "version": "1.0"
  }
}